ctc_detector/__init__.py
ctc_detector/__main__.py
ctc_detector/config.py
ctc_detector/config_default.ini
ctc_detector/dataset.py
ctc_detector/distribution.py
ctc_detector/helper.py
ctc_detector/loss.py
ctc_detector/model.py
ctc_detector/stat.py
ctc_detector/train.py
ctc_detector/transform.py
ctc_detector/valid.py
ctc_detector/version.py
ctc_detector/preprocess/__init__.py
ctc_detector/preprocess/backprop_label.py
ctc_detector/preprocess/crop_cell.py
ctc_detector/preprocess/dup_sample.py
ctc_detector/preprocess/etl_zip.py
ctc_detector/preprocess/migrate_label.py
ctc_detector/preprocess/nd2_processor.py
ctc_detector/preprocess/nikon_processor.py
ctc_detector/preprocess/nuclei_matcher.py
ctc_detector-0.1.14.dist-info/METADATA
ctc_detector-0.1.14.dist-info/WHEEL
ctc_detector-0.1.14.dist-info/top_level.txt
ctc_detector-0.1.14.dist-info/RECORD
