Metadata-Version: 2.1
Name: ctc-detector
Version: 0.1.14
Summary: Target Cell Detection
Home-page: http://www.aixmed.com
Author: Jimmy Lee
Author-email: jimmy.lee@aixmed.com
License: © 2018 AIxMed, Inc. All Rights Reserved
Platform: UNKNOWN
Requires-Dist: numpy (>=1.13)
Requires-Dist: matplotlib (>=2.1)
Requires-Dist: Scipy (>=0.19)
Requires-Dist: scikit-image (==0.13.1)
Requires-Dist: pandas (>=0.20)
Requires-Dist: Pillow (>=5.0)
Requires-Dist: tensorboardX (>=1.1)
Requires-Dist: tqdm (>=4.0)
Requires-Dist: scikit-learn (>=0.19)
Requires-Dist: xlsx2csv (>=0.7)
